flask_phrase/__init__.py
flask_phrase/flask_phrase.py
Flask_Phrase-2.0.1.dist-info/LICENSE
Flask_Phrase-2.0.1.dist-info/METADATA
Flask_Phrase-2.0.1.dist-info/WHEEL
Flask_Phrase-2.0.1.dist-info/top_level.txt
Flask_Phrase-2.0.1.dist-info/RECORD
