Metadata-Version: 2.1
Name: Flask-Phrase
Version: 2.0.1
Summary: Connect your Flask apps to Phrase with the powerful in-context-translation solution.
Author-email: Phrase <info@phrase.com>
Project-URL: Homepage, https://github.com/phrase/Flask-Phrase
Project-URL: Bug Tracker, https://github.com/phrase/Flask-Phrase/issues
Classifier: Environment :: Web Environment
Classifier: Framework :: Flask
Classifier: Intended Audience :: Developers
Classifier: License :: OSI Approved :: MIT License
Classifier: Operating System :: OS Independent
Classifier: Programming Language :: Python
Classifier: Topic :: Software Development :: Libraries :: Python Modules
Classifier: Topic :: Software Development :: Internationalization
Classifier: Topic :: Software Development :: Localization
Requires-Python: >=3.6
License-File: LICENSE
Requires-Dist: flask
Requires-Dist: flask-babel
